sc_audit/__init__.py
sc_audit/__main__.py
sc_audit/alembic.ini
sc_audit/backup/__init__.py
sc_audit/backup/download.py
sc_audit/backup/dump.py
sc_audit/backup/restore.py
sc_audit/cli.py
sc_audit/config.py
sc_audit/constants.py
sc_audit/db_schema/__init__.py
sc_audit/db_schema/association.py
sc_audit/db_schema/base.py
sc_audit/db_schema/distribution.py
sc_audit/db_schema/impact_project.py
sc_audit/db_schema/mint.py
sc_audit/db_schema/retirement.py
sc_audit/db_schema/sink.py
sc_audit/loader/__init__.py
sc_audit/loader/__main__.py
sc_audit/loader/distribution_outflows.py
sc_audit/loader/get_latest.py
sc_audit/loader/impact_projects.py
sc_audit/loader/minted_blocks.py
sc_audit/loader/retirement_from_block.py
sc_audit/loader/retirements.py
sc_audit/loader/sink_events.py
sc_audit/loader/sink_invocations.py
sc_audit/loader/sink_status.py
sc_audit/loader/sinking_txs.py
sc_audit/loader/utils.py
sc_audit/migrations/README.md
sc_audit/migrations/__init__.py
sc_audit/migrations/env.py
sc_audit/migrations/script.py.mako
sc_audit/migrations/versions/04d168a1598f_remove_retirement_beneficiary_length_.py
sc_audit/migrations/versions/0c2f50c4d517_fix_test_table_foreign_keys.py
sc_audit/migrations/versions/0e7b244f69dc_add_distribution_outflows_table.py
sc_audit/migrations/versions/19f853853773_add_test_prefix_tables.py
sc_audit/migrations/versions/371cdad348d3_rename_paging_token_columns_to_toid.py
sc_audit/migrations/versions/4813b9c06c97_change_paging_token_to_bigint.py
sc_audit/migrations/versions/52e5e68af772_switch_distributiontx_pk_to_paging_token.py
sc_audit/migrations/versions/713e40249322_add_paging_token_indexes.py
sc_audit/migrations/versions/77ea86674a18_add_contract_id_to_sinking_txs.py
sc_audit/migrations/versions/90594e768102_apply_branch_label.py
sc_audit/migrations/versions/b595c6a10724_create_initial_schema.py
sc_audit/session_manager.py
sc_audit/sources/__init__.py
sc_audit/sources/carbon_pool.py
sc_audit/sources/common.py
sc_audit/sources/minting_txs.py
sc_audit-0.14.0.dist-info/METADATA
sc_audit-0.14.0.dist-info/WHEEL
sc_audit-0.14.0.dist-info/entry_points.txt
sc_audit-0.14.0.dist-info/licenses/LICENSE
sc_audit-0.14.0.dist-info/RECORD
