Metadata-Version: 2.4
Name: sc-audit
Version: 0.14.0
Summary: Stellarcarbon database with monitoring and audit functionality
License: MIT
License-File: LICENSE
Author: Alex Olieman
Author-email: alex@olieman.net
Requires-Python: >=3.12,<4.0
Classifier: License :: OSI Approved :: MIT License
Classifier: Programming Language :: Python :: 3
Classifier: Programming Language :: Python :: 3.12
Classifier: Programming Language :: Python :: 3.13
Classifier: Programming Language :: Python :: 3.14
Requires-Dist: Cython (>=3.1.3,<4.0.0)
Requires-Dist: SQLAlchemy (>=2.0.43,<3.0.0)
Requires-Dist: alembic (>=1.16.4,<2.0.0)
Requires-Dist: click (>=8.2.1,<9.0.0)
Requires-Dist: httpx (>=0.28.1,<0.29.0)
Requires-Dist: pandas (>=2.3.1,<3.0.0)
Requires-Dist: parsel (>=1.10.0,<2.0.0)
Requires-Dist: psycopg[binary] (>=3.2.9,<4.0.0)
Requires-Dist: pydantic-settings (>=2.10.1,<3.0.0)
Requires-Dist: pygithub (>=2.8.1,<3.0.0)
Requires-Dist: stellar-sdk (>=13.0.0)
Project-URL: Homepage, https://www.stellarcarbon.io/
Project-URL: Repository, https://github.com/stellarcarbon/sc-audit
